sec_api/__init__.py
sec_api/index.py
sec_api-1.0.32.dist-info/LICENSE
sec_api-1.0.32.dist-info/METADATA
sec_api-1.0.32.dist-info/WHEEL
sec_api-1.0.32.dist-info/top_level.txt
sec_api-1.0.32.dist-info/RECORD
