Metadata-Version: 2.1
Name: sec-api
Version: 1.0.32
Summary: SEC EDGAR Filings API
Author: SEC API
Author-email: support@sec-api.io
Project-URL: Bug Reports, https://github.com/janlukasschroeder/sec-api-python/issues
Project-URL: Repository, https://github.com/janlukasschroeder/sec-api-python
Project-URL: Documentation, https://sec-api.io/docs
Keywords: SEC EDGAR API,SEC Filings API,SEC Filing Search API,SEC Full-Text Search API,EDGAR API,Finance,CIK,CUSIP,CUSIP to Ticker,CUSIP to CIK,10-Q,10-K,8-K,S-1,424B4,XBRL Converter,Financial Statements API,Insider Trading Data,Executive Compensation Data,Form D Offerings API,Form N-PORT API,Form ADV API,10-K/10-Q/8-K Section Extractor API
Classifier: Development Status :: 5 - Production/Stable
Classifier: Operating System :: OS Independent
Classifier: Topic :: Software Development :: Build Tools
Classifier: Topic :: Office/Business :: Financial
Classifier: Topic :: Office/Business :: Financial :: Investment
Classifier: Topic :: Software Development :: Libraries :: Python Modules
Classifier: Programming Language :: Python :: 3
Classifier: License :: OSI Approved :: MIT License
Classifier: Intended Audience :: Developers
Classifier: Intended Audience :: Financial and Insurance Industry
Classifier: Intended Audience :: Information Technology
License-File: LICENSE
